agentrun_plus/.env.dev
agentrun_plus/.env.prod
agentrun_plus/__init__.py
agentrun_plus/docker-compose.base.yml
agentrun_plus/docker-compose.dev.yml
agentrun_plus/docker-compose.prod.yml
agentrun_plus/docker-compose.sh
agentrun_plus/docker-compose.test.yml
agentrun_plus/docker-compose.yml
agentrun_plus/update_docker.sh
agentrun_plus/api/__init__.py
agentrun_plus/api/api.py
agentrun_plus/api/backend.py
agentrun_plus/api/main.py
agentrun_plus/code_runner/__init__.py
agentrun_plus/code_runner/api.py
agentrun_plus/code_runner/main.py
agentrun_plus/docker/api/Dockerfile
agentrun_plus/docker/api/pip.conf
agentrun_plus/docker/api/requirements.txt
agentrun_plus/docker/code_runner/Dockerfile
agentrun_plus/docker/code_runner/requirements.txt
agentrun_plus/docker/code_runner/runner_requirements.txt
agentrun_plus-0.2.23.dist-info/licenses/LICENSE
agentrun_plus-0.2.23.dist-info/METADATA
agentrun_plus-0.2.23.dist-info/WHEEL
agentrun_plus-0.2.23.dist-info/top_level.txt
agentrun_plus-0.2.23.dist-info/RECORD
