Metadata-Version: 2.4
Name: agentrun_plus
Version: 0.2.23
Summary: The easiest way to run AI or user generated python code safely in a docker container. This is a fork of the original AgentRun repo with additional customization options added.
Author-email: Jonathan Adly <gadly0123@gmail.com>, Vijay Ramasami <rvijayc@gmail.com>
License-Expression: Apache-2.0
Project-URL: Homepage, https://github.com/rvijayc/AgentRun
Project-URL: Changelog, https://github.com/rvijayc/AgentRun/releases
Project-URL: Issues, https://github.com/rvijayc/AgentRun/issues
Project-URL: CI, https://github.com/rvijayc/AgentRun/actions
Requires-Python: >=3.10
License-File: LICENSE
Requires-Dist: docker
Requires-Dist: RestrictedPython
Requires-Dist: loguru
Requires-Dist: fastapi
Requires-Dist: uvicorn
Provides-Extra: test
Requires-Dist: pytest>=7.4.3; extra == "test"
Requires-Dist: pytest-cov>=4.1.0; extra == "test"
Requires-Dist: pytest-mock>=3.12.0; extra == "test"
Requires-Dist: httpx>=0.25.2; extra == "test"
Requires-Dist: pytest-benchmark; extra == "test"
Requires-Dist: pytest-asyncio==0.21.1; extra == "test"
Requires-Dist: requests==2.31.0; extra == "test"
Requires-Dist: pytest-xdist==3.3.1; extra == "test"
Requires-Dist: pytest-timeout==2.2.0; extra == "test"
Provides-Extra: docs
Requires-Dist: mkdocs; extra == "docs"
Requires-Dist: mkdocs-material; extra == "docs"
Requires-Dist: mkdocstrings[python]; extra == "docs"
Requires-Dist: mkdocs-jupyter; extra == "docs"
Provides-Extra: dev
Requires-Dist: mypy; extra == "dev"
Provides-Extra: build
Requires-Dist: build; extra == "build"
Requires-Dist: twine; extra == "build"
Provides-Extra: all
Requires-Dist: agentrun_plus[test]; extra == "all"
Requires-Dist: agentrun_plus[dev]; extra == "all"
Requires-Dist: agentrun_plus[docs]; extra == "all"
Dynamic: license-file
